{"type": "Feature", "id": 12511400, "geometry": {"type": "Point", "coordinates": [26.872999, 43.563]}, "properties": {"woe:id": 12511400, "woe:parent_id": 835104, "woe:name": "Buynovitsa Airport", "woe:placetype": 14, "woe:placetype_name": "Airport", "woe:lang": "ENG", "iso:country": "BG", "meta:provider": ["geoplanet:7.3.1", "geoplanet:7.3.2", "geoplanet:7.4.0", "geoplanet:7.4.1", "geoplanet:7.5.1", "geoplanet:7.5.2", "geoplanet:7.6.0", "geoplanet:7.8.1", "geoplanet:7.9.0", "geoplanet:7.10.0", "geoplanet:8.0.0", "woeplanet:8.0.0"], "meta:indexed": "2020-08-20T21:03:31.659686", "meta:updated": "2020-10-14T12:07:44.348589", "woe:hierarchy": {"continent": 24865675, "country": 23424771, "town": 0, "planet": 1, "county": 55873856, "suburb": 0, "state": 20070052, "region": 0, "localadmin": 0}, "woe:timezone_id": 28350916, "woe:hash": "sxepgd2kf7b3", "woe:centroid": [26.872999, 43.563], "geom:latitude": 43.563, "geom:longitude": 26.872999, "geom:hash": "sxepgd2kf7b3", "woe:latitude": 43.563, "geom:centroid": [26.872999, 43.563], "woe:longitude": 26.872999, "woe:repo": "woeplanet-airport-bg", "geom:area": 0.0, "woe:scale": 19}}