{"type": "Feature", "id": 12511379, "geometry": {"type": "Point", "coordinates": [24.9564, 43.274399]}, "properties": {"woe:id": 12511379, "woe:parent_id": 834650, "woe:name": "Aleksandrovo Airport", "woe:placetype": 14, "woe:placetype_name": "Airport", "woe:lang": "ENG", "iso:country": "BG", "meta:provider": ["geoplanet:7.3.1", "geoplanet:7.3.2", "geoplanet:7.4.0", "geoplanet:7.4.1", "geoplanet:7.5.1", "geoplanet:7.5.2", "geoplanet:7.6.0", "geoplanet:7.8.1", "geoplanet:7.9.0", "geoplanet:7.10.0", "geoplanet:8.0.0", "woeplanet:8.0.0"], "meta:indexed": "2020-08-20T21:03:31.644505", "meta:updated": "2020-10-14T12:07:44.382926", "woe:hierarchy": {"continent": 24865675, "country": 23424771, "town": 0, "planet": 1, "county": 55873887, "suburb": 0, "state": 20070064, "region": 0, "localadmin": 0}, "woe:timezone_id": 28350916, "woe:hash": "sx9wpvuewk8t", "woe:centroid": [24.9564, 43.274399], "geom:latitude": 43.274399, "geom:longitude": 24.9564, "geom:hash": "sx9wpvuewk8t", "woe:latitude": 43.274399, "geom:centroid": [24.9564, 43.274399], "woe:longitude": 24.9564, "woe:repo": "woeplanet-airport-bg", "geom:area": 0.0, "woe:scale": 19}}