{"type": "Feature", "id": 12511519, "properties": {"woe:id": 12511519, "woe:parent_id": 839924, "woe:name": "Stozher Airport", "woe:placetype": 14, "woe:placetype_name": "Airport", "woe:lang": "ENG", "iso:country": "BG", "meta:provider": ["geoplanet:7.3.1", "geoplanet:7.3.2", "geoplanet:7.4.0", "geoplanet:7.4.1", "geoplanet:7.5.1", "geoplanet:7.5.2", "geoplanet:7.6.0", "geoplanet:7.8.1", "geoplanet:7.9.0", "geoplanet:7.10.0", "geoplanet:8.0.0", "woeplanet:8.0.0"], "meta:indexed": "2020-08-20T21:03:31.751150", "meta:updated": "2020-08-22T02:49:18.306214", "woe:hierarchy": {"continent": 24865675, "country": 23424771, "town": 0, "planet": 1, "county": 55873886, "suburb": 0, "state": 20070050, "region": 0, "localadmin": 0}, "woe:timezone_id": 28350916, "woe:hash": "sxez1mkv0nmz", "woe:centroid": [27.8349, 43.447701], "geom:latitude": 43.447701, "geom:longitude": 27.8349, "geom:hash": "sxez1mkv0nmz", "woe:latitude": 43.447701, "geom:centroid": [27.8349, 43.447701], "woe:longitude": 27.8349, "woe:repo": "woeplanet-airport-bg"}, "geometry": {"coordinates": [27.8349, 43.447701], "type": "Point"}}