{"type": "Feature", "id": 12511553, "geometry": {"type": "Point", "coordinates": [26.853901, 42.741901]}, "properties": {"woe:id": 12511553, "woe:parent_id": 840709, "woe:name": "Vulchin Airport", "woe:placetype": 14, "woe:placetype_name": "Airport", "woe:lang": "ENG", "iso:country": "BG", "meta:provider": ["geoplanet:7.3.1", "geoplanet:7.3.2", "geoplanet:7.4.0", "geoplanet:7.4.1", "geoplanet:7.5.1", "geoplanet:7.5.2", "geoplanet:7.6.0", "geoplanet:7.8.1", "geoplanet:7.9.0", "geoplanet:7.10.0", "geoplanet:8.0.0", "woeplanet:8.0.0"], "meta:indexed": "2020-08-20T21:03:31.778107", "meta:updated": "2020-10-14T12:07:44.305279", "woe:hierarchy": {"continent": 24865675, "country": 23424771, "town": 0, "planet": 1, "county": 55873734, "suburb": 0, "state": 20070075, "region": 0, "localadmin": 0}, "woe:timezone_id": 28350916, "woe:hash": "sxe55hfmt5zf", "woe:centroid": [26.853901, 42.741901], "geom:latitude": 42.741901, "geom:longitude": 26.853901, "geom:hash": "sxe55hfmt5zf", "woe:latitude": 42.741901, "geom:centroid": [26.853901, 42.741901], "woe:longitude": 26.853901, "woe:repo": "woeplanet-airport-bg", "geom:area": 0.0, "woe:scale": 19}}