{"type": "Feature", "id": 12511542, "properties": {"woe:id": 12511542, "woe:parent_id": 840478, "woe:name": "Velino Airport", "woe:placetype": 14, "woe:placetype_name": "Airport", "woe:lang": "ENG", "iso:country": "BG", "meta:provider": ["geoplanet:7.3.1", "geoplanet:7.3.2", "geoplanet:7.4.0", "geoplanet:7.4.1", "geoplanet:7.5.1", "geoplanet:7.5.2", "geoplanet:7.6.0", "geoplanet:7.8.1", "geoplanet:7.9.0", "geoplanet:7.10.0", "geoplanet:8.0.0", "woeplanet:8.0.0"], "meta:indexed": "2020-08-20T21:03:31.769489", "meta:updated": "2020-08-22T02:49:18.313203", "woe:hierarchy": {"continent": 24865675, "country": 23424771, "town": 0, "planet": 1, "county": 55873895, "suburb": 0, "state": 20070052, "region": 0, "localadmin": 0}, "woe:timezone_id": 28350916, "woe:hash": "sxepn9cb47sf", "woe:centroid": [27.006901, 43.427601], "geom:latitude": 43.427601, "geom:longitude": 27.006901, "geom:hash": "sxepn9cb47sf", "woe:latitude": 43.427601, "geom:centroid": [27.006901, 43.427601], "woe:longitude": 27.006901, "woe:repo": "woeplanet-airport-bg"}, "geometry": {"coordinates": [27.006901, 43.427601], "type": "Point"}}