{"type": "Feature", "id": 12511431, "geometry": {"type": "Point", "coordinates": [25.335899, 43.408199]}, "properties": {"woe:id": 12511431, "woe:parent_id": 836497, "woe:name": "Gorna Studena Airport", "woe:placetype": 14, "woe:placetype_name": "Airport", "woe:lang": "ENG", "iso:country": "BG", "meta:provider": ["geoplanet:7.3.1", "geoplanet:7.3.2", "geoplanet:7.4.0", "geoplanet:7.4.1", "geoplanet:7.5.1", "geoplanet:7.5.2", "geoplanet:7.6.0", "geoplanet:7.8.1", "geoplanet:7.9.0", "geoplanet:7.10.0", "geoplanet:8.0.0", "woeplanet:8.0.0"], "meta:indexed": "2020-08-20T21:03:31.682705", "meta:updated": "2020-10-14T12:07:44.328713", "woe:hierarchy": {"continent": 24865675, "country": 23424771, "town": 0, "planet": 1, "county": 55873917, "suburb": 0, "state": 20070063, "region": 0, "localadmin": 0}, "woe:timezone_id": 28350916, "woe:hash": "sxdnbw1p14z9", "woe:centroid": [25.335899, 43.408199], "geom:latitude": 43.408199, "geom:longitude": 25.335899, "geom:hash": "sxdnbw1p14z9", "woe:latitude": 43.408199, "geom:centroid": [25.335899, 43.408199], "woe:longitude": 25.335899, "woe:repo": "woeplanet-airport-bg", "geom:area": 0.0, "woe:scale": 19}}