{"type": "Feature", "id": 12511405, "properties": {"woe:id": 12511405, "woe:parent_id": 839370, "woe:name": "Cheshnegirovo Airport", "woe:placetype": 14, "woe:placetype_name": "Airport", "woe:lang": "ENG", "iso:country": "BG", "meta:provider": ["geoplanet:7.3.1", "geoplanet:7.3.2", "geoplanet:7.4.0", "geoplanet:7.4.1", "geoplanet:7.5.1", "geoplanet:7.5.2", "geoplanet:7.6.0", "geoplanet:7.8.1", "geoplanet:7.9.0", "geoplanet:7.10.0", "geoplanet:8.0.0", "woeplanet:8.0.0"], "meta:indexed": "2020-08-20T21:03:31.663721", "meta:updated": "2020-08-22T02:49:18.262539", "woe:hierarchy": {"continent": 24865675, "country": 23424771, "town": 0, "planet": 1, "county": 55873829, "suburb": 0, "state": 20070068, "region": 0, "localadmin": 0}, "woe:timezone_id": 28350916, "woe:hash": "sx3z86t4hfu7", "woe:centroid": [24.979, 42.113701], "geom:latitude": 42.113701, "geom:longitude": 24.979, "geom:hash": "sx3z86t4hfu7", "woe:latitude": 42.113701, "geom:centroid": [24.979, 42.113701], "woe:longitude": 24.979, "woe:repo": "woeplanet-airport-bg"}, "geometry": {"coordinates": [24.979, 42.113701], "type": "Point"}}