{"type": "Feature", "id": 12511433, "geometry": {"type": "Point", "coordinates": [24.6924, 42.290401]}, "properties": {"woe:id": 12511433, "woe:parent_id": 836643, "woe:name": "Graf Ignatievo Airport", "woe:placetype": 14, "woe:placetype_name": "Airport", "woe:lang": "ENG", "iso:country": "BG", "meta:provider": ["geoplanet:7.3.1", "geoplanet:7.3.2", "geoplanet:7.4.0", "geoplanet:7.4.1", "geoplanet:7.5.1", "geoplanet:7.5.2", "geoplanet:7.6.0", "geoplanet:7.8.1", "geoplanet:7.9.0", "geoplanet:7.10.0", "geoplanet:8.0.0", "woeplanet:8.0.0"], "meta:indexed": "2020-08-20T21:03:31.684057", "meta:updated": "2020-10-14T12:07:44.365245", "woe:hierarchy": {"continent": 24865675, "country": 23424771, "town": 0, "planet": 1, "county": 55873773, "suburb": 0, "state": 20070068, "region": 0, "localadmin": 0}, "woe:timezone_id": 28350916, "woe:hash": "sx989fsrqw5u", "woe:centroid": [24.6924, 42.290401], "geom:latitude": 42.290401, "geom:longitude": 24.6924, "geom:hash": "sx989fsrqw5u", "woe:latitude": 42.290401, "geom:centroid": [24.6924, 42.290401], "woe:longitude": 24.6924, "woe:repo": "woeplanet-airport-bg", "geom:area": 0.0, "woe:scale": 19}}