{"type": "Feature", "id": 12511455, "properties": {"woe:id": 12511455, "woe:parent_id": 835729, "woe:name": "Kumaritsa Airport", "woe:placetype": 14, "woe:placetype_name": "Airport", "woe:lang": "ENG", "iso:country": "BG", "meta:provider": ["geoplanet:7.3.1", "geoplanet:7.3.2", "geoplanet:7.4.0", "geoplanet:7.4.1", "geoplanet:7.5.1", "geoplanet:7.5.2", "geoplanet:7.6.0", "geoplanet:7.8.1", "geoplanet:7.9.0", "geoplanet:7.10.0", "geoplanet:8.0.0", "woeplanet:8.0.0"], "meta:indexed": "2020-08-20T21:03:31.702284", "meta:updated": "2020-08-22T02:49:18.281817", "woe:hierarchy": {"continent": 24865675, "country": 23424771, "town": 0, "planet": 1, "county": 55873710, "suburb": 0, "state": 20069794, "region": 0, "localadmin": 0}, "woe:timezone_id": 28350916, "woe:hash": "sx8ed5p41xu3", "woe:centroid": [23.300699, 42.819599], "geom:latitude": 42.819599, "geom:longitude": 23.300699, "geom:hash": "sx8ed5p41xu3", "woe:latitude": 42.819599, "geom:centroid": [23.300699, 42.819599], "woe:longitude": 23.300699, "woe:repo": "woeplanet-airport-bg"}, "geometry": {"coordinates": [23.300699, 42.819599], "type": "Point"}}