{"type": "Feature", "id": 12511437, "geometry": {"type": "Point", "coordinates": [26.733299, 42.4701]}, "properties": {"woe:id": 12511437, "woe:parent_id": 836772, "woe:name": "Irechekovo Airport", "woe:placetype": 14, "woe:placetype_name": "Airport", "woe:lang": "ENG", "iso:country": "BG", "meta:provider": ["geoplanet:7.3.1", "geoplanet:7.3.2", "geoplanet:7.4.0", "geoplanet:7.4.1", "geoplanet:7.5.1", "geoplanet:7.5.2", "geoplanet:7.6.0", "geoplanet:7.8.1", "geoplanet:7.9.0", "geoplanet:7.10.0", "geoplanet:8.0.0", "woeplanet:8.0.0"], "meta:indexed": "2020-08-20T21:03:31.686642", "meta:updated": "2020-10-14T12:07:44.360409", "woe:hierarchy": {"continent": 24865675, "country": 23424771, "town": 0, "planet": 1, "county": 55873701, "suburb": 0, "state": 20070074, "region": 0, "localadmin": 0}, "woe:timezone_id": 28350916, "woe:hash": "sxe1876w702w", "woe:centroid": [26.733299, 42.4701], "geom:latitude": 42.4701, "geom:longitude": 26.733299, "geom:hash": "sxe1876w702w", "woe:latitude": 42.4701, "geom:centroid": [26.733299, 42.4701], "woe:longitude": 26.733299, "woe:repo": "woeplanet-airport-bg", "geom:area": 0.0, "woe:scale": 19}}