{"type": "Feature", "id": 12511545, "geometry": {"type": "Point", "coordinates": [25.638201, 42.609299]}, "properties": {"woe:id": 12511545, "woe:parent_id": 836011, "woe:name": "Vetren Airport", "woe:placetype": 14, "woe:placetype_name": "Airport", "woe:lang": "ENG", "iso:country": "BG", "meta:provider": ["geoplanet:7.3.1", "geoplanet:7.3.2", "geoplanet:7.4.0", "geoplanet:7.4.1", "geoplanet:7.5.1", "geoplanet:7.5.2", "geoplanet:7.6.0", "geoplanet:7.8.1", "geoplanet:7.9.0", "geoplanet:7.10.0", "geoplanet:8.0.0", "woeplanet:8.0.0"], "meta:indexed": "2020-08-20T21:03:31.772050", "meta:updated": "2020-10-14T12:07:44.305696", "woe:hierarchy": {"continent": 24865675, "country": 23424771, "town": 0, "planet": 1, "county": 55873739, "suburb": 0, "state": 20070054, "region": 0, "localadmin": 0}, "woe:timezone_id": 28350916, "woe:hash": "sxd4rkv1jmh3", "woe:centroid": [25.638201, 42.609299], "geom:latitude": 42.609299, "geom:longitude": 25.638201, "geom:hash": "sxd4rkv1jmh3", "woe:latitude": 42.609299, "geom:centroid": [25.638201, 42.609299], "woe:longitude": 25.638201, "woe:repo": "woeplanet-airport-bg", "geom:area": 0.0, "woe:scale": 19}}